geo_code/__init__.py
geo_code/geocode.py
geo_code-0.0.5.dist-info/DESCRIPTION.rst
geo_code-0.0.5.dist-info/METADATA
geo_code-0.0.5.dist-info/RECORD
geo_code-0.0.5.dist-info/WHEEL
geo_code-0.0.5.dist-info/metadata.json
geo_code-0.0.5.dist-info/top_level.txt
