Metadata-Version: 2.0
Name: geo-code
Version: 0.0.5
Summary: Lightweight Python module for geocoding addresses via the Google Geocoding API
Home-page: https://github.com/jwilber/geo_code
Author: Jared Wilber
Author-email: jdwlbr@gmail.com
License: GNU3
Platform: UNKNOWN
Requires-Dist: pandas
Requires-Dist: requests
